sap_gui_library/__init__.py
sap_gui_library/sap_gui.py
sap_gui_library-0.1.3.dist-info/METADATA
sap_gui_library-0.1.3.dist-info/WHEEL
sap_gui_library-0.1.3.dist-info/top_level.txt
sap_gui_library-0.1.3.dist-info/RECORD
