Metadata-Version: 2.1
Name: sap-gui-library
Version: 0.1.3
Summary: Facilitating interaction with the SAP GUI system
Home-page: https://github.com/Chaparroo/sap-gui-library
Author: Felipe Chaparro
Author-email: felipelopezchaparro@gmail.com
Requires-Dist: pandas>=2.2.2
Requires-Dist: numpy>=2.1.1
Requires-Dist: python-dateutil==2.9.0.post0
Requires-Dist: pytz==2024.2
Requires-Dist: pywin32==306
Requires-Dist: six==1.16.0
Requires-Dist: tzdata==2024.1
